Workbook

Sheet Instrucciones
A1: Plantilla BOM · Bill of Materials
A2: Taller Integrado · Diseño + Ingeniería · ExploraTec UDD
A4: Regla de oro | B4: Otra persona debería entender qué comprar sin tener que preguntarle al diseñador.
A6: Leyenda
A7: Celda blanca | B7: Se completa a mano. Las columnas Subsistema, Unidad, Disponibilidad y Estado tienen lista desplegable.
A8: Celda gris | B8: Se calcula sola (fórmula). No editar.
A9: Celda amarilla | B9: Dato de encabezado del proyecto (nombre, equipo, versión, fecha).
A10: Texto azul | B10: Valor ingresado a mano que alimenta cálculos (cantidades y precios).
A12: Columnas del BOM
A13: ID | B13: Código único por ítem. Prefijo por subsistema: E electrónica · M mecánica · F fabricación · T terminaciones · A ensamblaje · O otros (E01, E02, M01…). No se reutiliza un ID eliminado.
A14: Subsistema | B14: Agrupa el BOM más allá de la electrónica y ayuda a repartir responsabilidades.
A15: Función (arquitectura) | B15: Qué función de la arquitectura cumple el ítem. Debe escribirse igual que en la hoja Trazabilidad.
A16: Componente | B16: Qué es, en términos genéricos (sensor ambiental, fuente, tornillo).
A17: Especificación | B17: Lo necesario para comprar sin preguntar: modelo, voltaje, medidas, material, norma (AHT10 I²C; M3 × 12 mm).
A18: Fabricante / MPN | B18: Marca y código de parte del fabricante, cuando exista.
A19: Cant. / Unidad | B19: Cantidad por prototipo y su unidad (un., m, m²…).
A20: Proveedor / Enlace | B20: Dónde se compra y enlace a la tienda o al datasheet.
A21: $ Unit. / $ Total | B21: Precio unitario en CLP con IVA; el total se calcula solo.
A22: Disponibilidad / Alternativa | B22: ¿Existe localmente? ¿Qué lo reemplaza si no hay stock?
A23: Estado | B23: Avance de la compra: por cotizar → cotizado → comprado → recibido → instalado.
A24: Trazabilidad | B24: Se calcula sola: ✓ si la función existe en la hoja Trazabilidad; «Revisar» si no.
... A28: Datos de ejemplo | B28: Las filas precargadas usan el caso guía de la clase (estación ambiental). Los precios del ESP32, AHT10 y WS2812B son los valores referenciales de la presentación; el resto queda por cotizar. Borren las filas de ejemplo al usar la plantilla.

Sheet BOM
A1: BILL OF MATERIALS
A2: Proyecto | B2: Sistema de Trazabilidad y Alerta en Montaña (Parque Mahuida) | E2: Costo total (CLP) | F2: =SUM(L9:L208) -> 432314
A3: Equipo | B3: Victoria Atala, Valeria Cheetham, Maximiliano Greve, Laura Hoppe | E3: N° de ítems | F3: =COUNTA(D9:D208) -> 36
A4: Versión | B4: BOM_v1.1 | E4: Ítems sin precio | F4: =SUMPRODUCT((D9:D208<>"")*(K9:K208="")) -> 0
A5: Fecha | B5: 01-10-2026 | E5: Ítems por revisar (trazab.) | F5: =COUNTIF(P9:P208,"Revisar") -> 0
A8: ID | B8: Subsistema | C8: Función (arquitectura) | D8: Componente | E8: Especificación | F8: Fabricante / MPN | G8: Cant. | H8: Unidad | I8: Proveedor | J8: Enlace (tienda o datasheet) | K8: $ Unit. (CLP) | L8: $ Total (CLP) | M8: Disponibilidad | N8: Alternativa / reemplazo | O8: Estado | P8: Trazabilidad | Q8: Notas
A9: E01 | B9: Electrónica | C9: Procesar y comunicar vía LoRa | D9: Microcontrolador LoRa del tótem | E9: Heltec WiFi LoRa 32 V3 (ESP32-S3 + SX1262 LoRa 915 MHz + OLED 0.96" + BLE 5). Incluye antena y conector de batería | F9: Heltec Automation / WiFi LoRa 32 V3 | G9: 2 | H9: un. | I9: Zona Industrial | J9: https://www.zonaindustrial.cl/shop/heltec-wi-fi-lora-32-v3-meshtastic-con-carcasa-y-antena-57777 | K9: 38080 | L9: =IF(OR(G9="",K9=""),"",G9*K9) -> 76160 | M9: Disponible en Chile | N9: Heltec V4 (comprobar stock); HUBOT $33.400 (agotado) | O9: Cotizado | P9: =IF(C9="","",IF(COUNTIF(Trazabilidad!$A$5:$A$60,C9)>0,"✓","Revisar")) -> ✓ | Q9: Ahora además escanea BLE (clips), lee BME280 y RTC y DECIDE seguro/inseguro. NUNCA transmitir sin antena. Alimentar a 5 V (no 12 V). Con BLE scan activo consume ~0,1–0,15 A: medir.
A10: E02 | B10: Electrónica | C10: Procesar y comunicar vía LoRa | D10: Microcontrolador LoRa de la base (gateway) | E10: Heltec WiFi LoRa 32 V3, igual al del tótem; conectada por USB al PC | F10: Heltec Automation / WiFi LoRa 32 V3 | G10: 1 | H10: un. | I10: Zona Industrial | J10: https://www.zonaindustrial.cl/shop/heltec-wi-fi-lora-32-v3-meshtastic-con-carcasa-y-antena-57777 | K10: 38080 | L10: =IF(OR(G10="",K10=""),"",G10*K10) -> 38080 | M10: Disponible en Chile | N10: HUBOT $33.400 (agotado) | O10: Cotizado | P10: =IF(C10="","",IF(COUNTIF(Trazabilidad!$A$5:$A$60,C10)>0,"✓","Revisar")) -> ✓ | Q10: En v01 era una de las 2 Heltec de E01; se separa para trazar la base. Recibe LoRa de los tótems y los entrega al PC por USB. Puede escanear BLE en la caseta para detectar el regreso del clip.
A11: E03 | B11: Electrónica | C11: Identificar paso de senderista (clip BLE) | D11: Microcontrolador BLE del clip | E11: Seeed XIAO ESP32-C3 (BLE 5, cargador LiPo integrado, 21x17.8 mm) | F11: Seeed Studio / XIAO ESP32-C3 | G11: 3 | H11: un. | I11: MechatronicStore | J11: https://www.mechatronicstore.cl/seeed-studio-xiao-esp32-c3/ | K11: 9490 | L11: =IF(OR(G11="",K11=""),"",G11*K11) -> 28470 | M11: Disponible en Chile | N11: XIAO nRF52840; beacon pasivo Altronics BCN02 $18.257 (no recibe alertas) | O11: Cotizado | P11: =IF(C11="","",IF(COUNTIF(Trazabilidad!$A$5:$A$60,C11)>0,"✓","Revisar")) -> ✓ | Q11: Reemplaza al lector RFID RC522 y a la pulsera pasiva. Emite su ID por BLE cada ~1 s y escucha si el tótem avisa "condición insegura". Requiere programarlo (Arduino).
A12: E04 | B12: Electrónica | C12: Alimentar y encender el clip | D12: Batería LiPo del clip | E12: LiPo plana 3.7 V 400–600 mAh, conector JST PH2.0, con protección | F12: Genérico | G12: 3 | H12: un. | I12: HUBOT (buscar) | J12: https://hubot.cl/categoria-producto/insumos-y-accesorios/baterias-pilas/ | K12: 5000 | L12: =IF(OR(G12="",K12=""),"",G12*K12) -> 15000 | M12: Por verificar | N12: 18650 + portapila ($690 HUBOT; clip más grueso) | O12: Por cotizar | P12: =IF(C12="","",IF(COUNTIF(Trazabilidad!$A$5:$A$60,C12)>0,"✓","Revisar")) -> ✓ | Q12: No hallé LiPo chica con ficha en tienda chilena. Revisar polaridad ANTES de conectar al XIAO (cada fabricante invierte los cables). Precio estimado, no verificado.
A13: E05 | B13: Electrónica | C13: Medir clima y presión atmosférica | D13: Sensor ambiental barométrico | E13: Sensor BME280 (presión, temperatura, humedad; I2C, 3.3 V) | F13: Bosch Sensortec / BME280 | G13: 2 | H13: un. | I13: Afel Electrónica | J13: https://afel.cl/products/sensor-barometrico-bme280 | K13: 8650 | L13: =IF(OR(G13="",K13=""),"",G13*K13) -> 17300 | M13: Disponible en Chile | N13: MechatronicStore $8.690 (sin stock al revisar) | O13: Cotizado | P13: =IF(C13="","",IF(COUNTIF(Trazabilidad!$A$5:$A$60,C13)>0,"✓","Revisar")) -> ✓ | Q13: Cantidad 1→2 (uno por tótem). Debe ir FUERA de la caja sellada o con visera ventilada (sin impresión 3D: p. ej. caja plástica abierta por abajo), si no se calienta y miente. Dirección I2C 0x76/0x77.
A14: E06 | B14: Electrónica | C14: Poner hora real y guardar registros (RTC) | D14: Reloj de tiempo real (RTC) | E14: Módulo DS3231 I2C con pila CR2032 | F14: Maxim / DS3231 | G14: 2 | H14: un. | I14: AFEL | J14: https://afel.cl/collections/rtc | K14: 3500 | L14: =IF(OR(G14="",K14=""),"",G14*K14) -> 7000 | M14: Por verificar | N14: Hora por NTP desde el PC vía LoRa (menos preciso) | O14: Por cotizar | P14: =IF(C14="","",IF(COUNTIF(Trazabilidad!$A$5:$A$60,C14)>0,"✓","Revisar")) -> ✓ | Q14: Sin RTC, si se corta el enlace con el PC el tótem no sabe la hora y "guardar y reenviar" no sirve. Comparte bus I2C con el BME280. Incluir pila CR2032. Precio estimado, no verificado.
A15: E07 | B15: Electrónica | C15: Emitir señal de auxilio manual (SOS en tótem) | D15: Pulsador SOS del tótem | E15: Pulsador 22 mm NA con tapa de protección, IP65, 5–24 V (rojo) | F15: Genérico | G15: 2 | H15: un. | I15: Zona Industrial | J15: https://www.zonaindustrial.cl/shop/category/4324 | K15: 5000 | L15: =IF(OR(G15="",K15=""),"",G15*K15) -> 10000 | M15: Por verificar | N15: Pulsador metálico 16 mm IP65 (el de v01, $2.990) | O15: Por cotizar | P15: =IF(C15="","",IF(COUNTIF(Trazabilidad!$A$5:$A$60,C15)>0,"✓","Revisar")) -> ✓ | Q15: Cant. 1→2 (SOS en cada tótem). Contacto NA a GPIO con pull-up; exigir pulsación ~3 s para evitar falsos SOS. Reemplaza a E05 de v01 (que tenía MPN erróneo WS2812B y enlace a la portada). Precio estimado, no verificado.
A16: E08 | B16: Electrónica | C16: Mostrar estado y alertas locales | D16: LED RGB de estado + resistencias | E16: LED RGB ánodo común 10 mm + resistencias 220 Ω | F16: Genérico | G16: 2 | H16: set | I16: AFEL | J16: https://afel.cl/collections/leds | K16: 1500 | L16: =IF(OR(G16="",K16=""),"",G16*K16) -> 3000 | M16: Por verificar | N16: Módulo 4 LEDs WS2812B (el de v01, $1.000); baliza LED 12 V | O16: Por cotizar | P16: =IF(C16="","",IF(COUNTIF(Trazabilidad!$A$5:$A$60,C16)>0,"✓","Revisar")) -> ✓ | Q16: Verde = seguro, ámbar/rojo = condición insegura, azul = SOS enviado. La OLED no se ve a pleno sol: el LED es el aviso principal. Precio estimado, no verificado.
A17: E09 | B17: Electrónica | C17: Mostrar estado y alertas locales | D17: Buzzer del tótem (alto volumen) | E17: Buzzer activo 5 V ~85–90 dB | F17: Genérico | G17: 2 | H17: un. | I17: AFEL | J17: https://afel.cl/collections/buzzer-zumbador | K17: 1500 | L17: =IF(OR(G17="",K17=""),"",G17*K17) -> 3000 | M17: Por verificar | N17: Sirena piezo 12 V | O17: Por cotizar | P17: =IF(C17="","",IF(COUNTIF(Trazabilidad!$A$5:$A$60,C17)>0,"✓","Revisar")) -> ✓ | Q17: NO se conecta directo al GPIO (3.3 V, pocos mA): va por transistor (E10). Cant. 1→2. Precio estimado, no verificado.
A18: E10 | B18: Electrónica | C18: Mostrar estado y alertas locales | D18: Transistores / módulo MOSFET | E18: Set 2N2222 (o módulo MOSFET) + resistencias de base | F18: Genérico | G18: 2 | H18: set | I18: AFEL | J18: https://afel.cl/collections/mosfet | K18: 1500 | L18: =IF(OR(G18="",K18=""),"",G18*K18) -> 3000 | M18: Por verificar | N18: Módulo relé 5 V | O18: Por cotizar | P18: =IF(C18="","",IF(COUNTIF(Trazabilidad!$A$5:$A$60,C18)>0,"✓","Revisar")) -> ✓ | Q18: Faltaba en v1.0: un GPIO no entrega corriente suficiente para buzzer fuerte ni LED de alto brillo. Precio estimado, no verificado.
A19: E11 | B19: Electrónica | C19: Alertar al senderista con pitido (clip) | D19: Buzzer del clip | E19: Buzzer activo piezo 3–5 V ~12 mm | F19: Genérico | G19: 3 | H19: un. | I19: AFEL | J19: https://afel.cl/collections/buzzer-zumbador | K19: 800 | L19: =IF(OR(G19="",K19=""),"",G19*K19) -> 2400 | M19: Por verificar | N19: Motor de vibración | O19: Por cotizar | P19: =IF(C19="","",IF(COUNTIF(Trazabilidad!$A$5:$A$60,C19)>0,"✓","Revisar")) -> ✓ | Q19: Pita cuando el tótem avisa "condición insegura". Un piezo chico se oye poco con ruido: probar. A GPIO del XIAO (máx ~20 mA). Precio estimado, no verificado.
A20: E12 | B20: Electrónica | C20: Alimentar y encender el clip | D20: Interruptor del clip | E20: Slide switch mini 3 pines, 1 polo 2 posiciones | F20: Genérico | G20: 3 | H20: un. | I20: AFEL | J20: https://afel.cl/collections/botones-interruptores | K20: 500 | L20: =IF(OR(G20="",K20=""),"",G20*K20) -> 1500 | M20: Por verificar | N20: Apagar quitando la batería | O20: Por cotizar | P20: =IF(C20="","",IF(COUNTIF(Trazabilidad!$A$5:$A$60,C20)>0,"✓","Revisar")) -> ✓ | Q20: En serie con el positivo de la batería; sin él la batería se descarga sola. Precio estimado, no verificado.
... A44: T01 | B44: Terminaciones | C44: Proteger componentes contra intemperie | D44: Silicona neutra + gel de sílice | E44: Sellador de silicona neutra y sobres de gel de sílice | F44: Genérico | G44: 1 | H44: set | I44: Ferretería | J44: Sin enlace verificado | K44: 3500 | L44: =IF(OR(G44="",K44=""),"",G44*K44) -> 3500 | M44: Por verificar | N44: Cinta autovulcanizante | O44: Por cotizar | P44: =IF(C44="","",IF(COUNTIF(Trazabilidad!$A$5:$A$60,C44)>0,"✓","Revisar")) -> ✓ | Q44: La condensación dentro de la caja es la causa más común de fallas en terreno. Precio estimado, no verificado.
L45: =IF(OR(G45="",K45=""),"",G45*K45) | P45: =IF(C45="","",IF(COUNTIF(Trazabilidad!$A$5:$A$60,C45)>0,"✓","Revisar"))
L46: =IF(OR(G46="",K46=""),"",G46*K46) | P46: =IF(C46="","",IF(COUNTIF(Trazabilidad!$A$5:$A$60,C46)>0,"✓","Revisar"))
L47: =IF(OR(G47="",K47=""),"",G47*K47) | P47: =IF(C47="","",IF(COUNTIF(Trazabilidad!$A$5:$A$60,C47)>0,"✓","Revisar"))
L48: =IF(OR(G48="",K48=""),"",G48*K48) | P48: =IF(C48="","",IF(COUNTIF(Trazabilidad!$A$5:$A$60,C48)>0,"✓","Revisar"))
L49: =IF(OR(G49="",K49=""),"",G49*K49) | P49: =IF(C49="","",IF(COUNTIF(Trazabilidad!$A$5:$A$60,C49)>0,"✓","Revisar"))
L50: =IF(OR(G50="",K50=""),"",G50*K50) | P50: =IF(C50="","",IF(COUNTIF(Trazabilidad!$A$5:$A$60,C50)>0,"✓","Revisar"))
L51: =IF(OR(G51="",K51=""),"",G51*K51) | P51: =IF(C51="","",IF(COUNTIF(Trazabilidad!$A$5:$A$60,C51)>0,"✓","Revisar"))
L52: =IF(OR(G52="",K52=""),"",G52*K52) | P52: =IF(C52="","",IF(COUNTIF(Trazabilidad!$A$5:$A$60,C52)>0,"✓","Revisar"))
L53: =IF(OR(G53="",K53=""),"",G53*K53) | P53: =IF(C53="","",IF(COUNTIF(Trazabilidad!$A$5:$A$60,C53)>0,"✓","Revisar"))
L54: =IF(OR(G54="",K54=""),"",G54*K54) | P54: =IF(C54="","",IF(COUNTIF(Trazabilidad!$A$5:$A$60,C54)>0,"✓","Revisar"))
L55: =IF(OR(G55="",K55=""),"",G55*K55) | P55: =IF(C55="","",IF(COUNTIF(Trazabilidad!$A$5:$A$60,C55)>0,"✓","Revisar"))
L56: =IF(OR(G56="",K56=""),"",G56*K56) | P56: =IF(C56="","",IF(COUNTIF(Trazabilidad!$A$5:$A$60,C56)>0,"✓","Revisar"))
... L208: =IF(OR(G208="",K208=""),"",G208*K208) | P208: =IF(C208="","",IF(COUNTIF(Trazabilidad!$A$5:$A$60,C208)>0,"✓","Revisar"))

Sheet Fases
A1: Fases de compra
A2: Fase 1 = lo que se compra ahora para probar el alcance LoRa (caseta ↔ Cerro La Cruz) y la detección BLE. Fase 2 = lo que se compra después, solo si la prueba funciona. El tótem de prueba se alimenta con powerbank o USB (no incluido).
A4: FASE 1 · Comprar ahora (prueba de alcance LoRa + BLE)
A5: ID | B5: Componente | C5: Proveedor | D5: Cant. | E5: $ Unit. (CLP) | F5: $ Subtotal (CLP) | G5: Enlace (tienda o datasheet) | H5: Para qué / cuándo
A6: E01 | B6: =INDEX(BOM!$D$9:$D$208,MATCH($A6,BOM!$A$9:$A$208,0)) -> Microcontrolador LoRa del tótem | C6: =INDEX(BOM!$I$9:$I$208,MATCH($A6,BOM!$A$9:$A$208,0)) -> Zona Industrial | D6: 1 | E6: =INDEX(BOM!$K$9:$K$208,MATCH($A6,BOM!$A$9:$A$208,0)) -> 38080 | F6: =D6*E6 -> 38080 | G6: =INDEX(BOM!$J$9:$J$208,MATCH($A6,BOM!$A$9:$A$208,0)) -> https://www.zonaindustrial.cl/shop/heltec-wi-fi-lora-32-v3-meshtastic-con-carcasa-y-antena-57777 | H6: Tótem de prueba (1 de 2): decide seguro/inseguro y habla por LoRa
A7: E02 | B7: =INDEX(BOM!$D$9:$D$208,MATCH($A7,BOM!$A$9:$A$208,0)) -> Microcontrolador LoRa de la base (gateway) | C7: =INDEX(BOM!$I$9:$I$208,MATCH($A7,BOM!$A$9:$A$208,0)) -> Zona Industrial | D7: 1 | E7: =INDEX(BOM!$K$9:$K$208,MATCH($A7,BOM!$A$9:$A$208,0)) -> 38080 | F7: =D7*E7 -> 38080 | G7: =INDEX(BOM!$J$9:$J$208,MATCH($A7,BOM!$A$9:$A$208,0)) -> https://www.zonaindustrial.cl/shop/heltec-wi-fi-lora-32-v3-meshtastic-con-carcasa-y-antena-57777 | H7: Base: recibe LoRa y la pasa al PC
A8: E03 | B8: =INDEX(BOM!$D$9:$D$208,MATCH($A8,BOM!$A$9:$A$208,0)) -> Microcontrolador BLE del clip | C8: =INDEX(BOM!$I$9:$I$208,MATCH($A8,BOM!$A$9:$A$208,0)) -> MechatronicStore | D8: 1 | E8: =INDEX(BOM!$K$9:$K$208,MATCH($A8,BOM!$A$9:$A$208,0)) -> 9490 | F8: =D8*E8 -> 9490 | G8: =INDEX(BOM!$J$9:$J$208,MATCH($A8,BOM!$A$9:$A$208,0)) -> https://www.mechatronicstore.cl/seeed-studio-xiao-esp32-c3/ | H8: Clip BLE de prueba
A9: E04 | B9: =INDEX(BOM!$D$9:$D$208,MATCH($A9,BOM!$A$9:$A$208,0)) -> Batería LiPo del clip | C9: =INDEX(BOM!$I$9:$I$208,MATCH($A9,BOM!$A$9:$A$208,0)) -> HUBOT (buscar) | D9: 1 | E9: =INDEX(BOM!$K$9:$K$208,MATCH($A9,BOM!$A$9:$A$208,0)) -> 5000 | F9: =D9*E9 -> 5000 | G9: =INDEX(BOM!$J$9:$J$208,MATCH($A9,BOM!$A$9:$A$208,0)) -> https://hubot.cl/categoria-producto/insumos-y-accesorios/baterias-pilas/ | H9: Batería del clip
A10: E05 | B10: =INDEX(BOM!$D$9:$D$208,MATCH($A10,BOM!$A$9:$A$208,0)) -> Sensor ambiental barométrico | C10: =INDEX(BOM!$I$9:$I$208,MATCH($A10,BOM!$A$9:$A$208,0)) -> Afel Electrónica | D10: 1 | E10: =INDEX(BOM!$K$9:$K$208,MATCH($A10,BOM!$A$9:$A$208,0)) -> 8650 | F10: =D10*E10 -> 8650 | G10: =INDEX(BOM!$J$9:$J$208,MATCH($A10,BOM!$A$9:$A$208,0)) -> https://afel.cl/products/sensor-barometrico-bme280 | H10: Sensor de clima del tótem de prueba
A11: E11 | B11: =INDEX(BOM!$D$9:$D$208,MATCH($A11,BOM!$A$9:$A$208,0)) -> Buzzer del clip | C11: =INDEX(BOM!$I$9:$I$208,MATCH($A11,BOM!$A$9:$A$208,0)) -> AFEL | D11: 1 | E11: =INDEX(BOM!$K$9:$K$208,MATCH($A11,BOM!$A$9:$A$208,0)) -> 800 | F11: =D11*E11 -> 800 | G11: =INDEX(BOM!$J$9:$J$208,MATCH($A11,BOM!$A$9:$A$208,0)) -> https://afel.cl/collections/buzzer-zumbador | H11: Pitido de aviso del clip
A12: E12 | B12: =INDEX(BOM!$D$9:$D$208,MATCH($A12,BOM!$A$9:$A$208,0)) -> Interruptor del clip | C12: =INDEX(BOM!$I$9:$I$208,MATCH($A12,BOM!$A$9:$A$208,0)) -> AFEL | D12: 1 | E12: =INDEX(BOM!$K$9:$K$208,MATCH($A12,BOM!$A$9:$A$208,0)) -> 500 | F12: =D12*E12 -> 500 | G12: =INDEX(BOM!$J$9:$J$208,MATCH($A12,BOM!$A$9:$A$208,0)) -> https://afel.cl/collections/botones-interruptores | H12: Encender/apagar el clip
A13: E17 | B13: =INDEX(BOM!$D$9:$D$208,MATCH($A13,BOM!$A$9:$A$208,0)) -> Cable USB-C de datos | C13: =INDEX(BOM!$I$9:$I$208,MATCH($A13,BOM!$A$9:$A$208,0)) -> Retail / MercadoLibre | D13: 1 | E13: =INDEX(BOM!$K$9:$K$208,MATCH($A13,BOM!$A$9:$A$208,0)) -> 3000 | F13: =D13*E13 -> 3000 | G13: =INDEX(BOM!$J$9:$J$208,MATCH($A13,BOM!$A$9:$A$208,0)) -> Sin enlace verificado | H13: Conectar la base al PC (omitir si ya tienen un cable de datos)
A14: M03 | B14: =INDEX(BOM!$D$9:$D$208,MATCH($A14,BOM!$A$9:$A$208,0)) -> Pinza / clip de sujeción | C14: =INDEX(BOM!$I$9:$I$208,MATCH($A14,BOM!$A$9:$A$208,0)) -> Mercería / ferretería | D14: 1 | E14: =INDEX(BOM!$K$9:$K$208,MATCH($A14,BOM!$A$9:$A$208,0)) -> 800 | F14: =D14*E14 -> 800 | G14: =INDEX(BOM!$J$9:$J$208,MATCH($A14,BOM!$A$9:$A$208,0)) -> Sin enlace verificado | H14: Fijar el clip a la ropa
A15: M04 | B15: =INDEX(BOM!$D$9:$D$208,MATCH($A15,BOM!$A$9:$A$208,0)) -> Mini caja plástica para el clip | C15: =INDEX(BOM!$I$9:$I$208,MATCH($A15,BOM!$A$9:$A$208,0)) -> AFEL | D15: 1 | E15: =INDEX(BOM!$K$9:$K$208,MATCH($A15,BOM!$A$9:$A$208,0)) -> 1500 | F15: =D15*E15 -> 1500 | G15: =INDEX(BOM!$J$9:$J$208,MATCH($A15,BOM!$A$9:$A$208,0)) -> https://afel.cl/collections/cajas-proyectos | H15: Carcasa del clip
A16: A01 | B16: =INDEX(BOM!$D$9:$D$208,MATCH($A16,BOM!$A$9:$A$208,0)) -> Cables Dupont | C16: =INDEX(BOM!$I$9:$I$208,MATCH($A16,BOM!$A$9:$A$208,0)) -> AFEL | D16: 1 | E16: =INDEX(BOM!$K$9:$K$208,MATCH($A16,BOM!$A$9:$A$208,0)) -> 2500 | F16: =D16*E16 -> 2500 | G16: =INDEX(BOM!$J$9:$J$208,MATCH($A16,BOM!$A$9:$A$208,0)) -> https://afel.cl/collections/cables | H16: Pruebas en protoboard, sin soldar
A17: Total fase 1 | F17: =SUM(F6:F16) -> 108400
A19: FASE 2 · Comprar después (solo si la fase 1 funciona)
A20: ID | B20: Componente | C20: Proveedor | D20: Cant. | E20: $ Unit. (CLP) | F20: $ Subtotal (CLP) | G20: Enlace (tienda o datasheet) | H20: Para qué / cuándo
A21: E01 | B21: =INDEX(BOM!$D$9:$D$208,MATCH($A21,BOM!$A$9:$A$208,0)) -> Microcontrolador LoRa del tótem | C21: =INDEX(BOM!$I$9:$I$208,MATCH($A21,BOM!$A$9:$A$208,0)) -> Zona Industrial | D21: =INDEX(BOM!$G$9:$G$208,MATCH($A21,BOM!$A$9:$A$208,0))-SUMIF($A$6:$A$16,$A21,$D$6:$D$16) -> 1 | E21: =INDEX(BOM!$K$9:$K$208,MATCH($A21,BOM!$A$9:$A$208,0)) -> 38080 | F21: =D21*E21 -> 38080 | G21: =INDEX(BOM!$J$9:$J$208,MATCH($A21,BOM!$A$9:$A$208,0)) -> https://www.zonaindustrial.cl/shop/heltec-wi-fi-lora-32-v3-meshtastic-con-carcasa-y-antena-57777 | H21: Segundo tótem
A22: E03 | B22: =INDEX(BOM!$D$9:$D$208,MATCH($A22,BOM!$A$9:$A$208,0)) -> Microcontrolador BLE del clip | C22: =INDEX(BOM!$I$9:$I$208,MATCH($A22,BOM!$A$9:$A$208,0)) -> MechatronicStore | D22: =INDEX(BOM!$G$9:$G$208,MATCH($A22,BOM!$A$9:$A$208,0))-SUMIF($A$6:$A$16,$A22,$D$6:$D$16) -> 2 | E22: =INDEX(BOM!$K$9:$K$208,MATCH($A22,BOM!$A$9:$A$208,0)) -> 9490 | F22: =D22*E22 -> 18980 | G22: =INDEX(BOM!$J$9:$J$208,MATCH($A22,BOM!$A$9:$A$208,0)) -> https://www.mechatronicstore.cl/seeed-studio-xiao-esp32-c3/ | H22: Clips 2 y 3
A23: E04 | B23: =INDEX(BOM!$D$9:$D$208,MATCH($A23,BOM!$A$9:$A$208,0)) -> Batería LiPo del clip | C23: =INDEX(BOM!$I$9:$I$208,MATCH($A23,BOM!$A$9:$A$208,0)) -> HUBOT (buscar) | D23: =INDEX(BOM!$G$9:$G$208,MATCH($A23,BOM!$A$9:$A$208,0))-SUMIF($A$6:$A$16,$A23,$D$6:$D$16) -> 2 | E23: =INDEX(BOM!$K$9:$K$208,MATCH($A23,BOM!$A$9:$A$208,0)) -> 5000 | F23: =D23*E23 -> 10000 | G23: =INDEX(BOM!$J$9:$J$208,MATCH($A23,BOM!$A$9:$A$208,0)) -> https://hubot.cl/categoria-producto/insumos-y-accesorios/baterias-pilas/ | H23: Baterías de los clips 2 y 3
A24: E05 | B24: =INDEX(BOM!$D$9:$D$208,MATCH($A24,BOM!$A$9:$A$208,0)) -> Sensor ambiental barométrico | C24: =INDEX(BOM!$I$9:$I$208,MATCH($A24,BOM!$A$9:$A$208,0)) -> Afel Electrónica | D24: =INDEX(BOM!$G$9:$G$208,MATCH($A24,BOM!$A$9:$A$208,0))-SUMIF($A$6:$A$16,$A24,$D$6:$D$16) -> 1 | E24: =INDEX(BOM!$K$9:$K$208,MATCH($A24,BOM!$A$9:$A$208,0)) -> 8650 | F24: =D24*E24 -> 8650 | G24: =INDEX(BOM!$J$9:$J$208,MATCH($A24,BOM!$A$9:$A$208,0)) -> https://afel.cl/products/sensor-barometrico-bme280 | H24: Sensor del segundo tótem
A25: E06 | B25: =INDEX(BOM!$D$9:$D$208,MATCH($A25,BOM!$A$9:$A$208,0)) -> Reloj de tiempo real (RTC) | C25: =INDEX(BOM!$I$9:$I$208,MATCH($A25,BOM!$A$9:$A$208,0)) -> AFEL | D25: =INDEX(BOM!$G$9:$G$208,MATCH($A25,BOM!$A$9:$A$208,0))-SUMIF($A$6:$A$16,$A25,$D$6:$D$16) -> 2 | E25: =INDEX(BOM!$K$9:$K$208,MATCH($A25,BOM!$A$9:$A$208,0)) -> 3500 | F25: =D25*E25 -> 7000 | G25: =INDEX(BOM!$J$9:$J$208,MATCH($A25,BOM!$A$9:$A$208,0)) -> https://afel.cl/collections/rtc | H25: Electrónica completa del tótem
A26: E07 | B26: =INDEX(BOM!$D$9:$D$208,MATCH($A26,BOM!$A$9:$A$208,0)) -> Pulsador SOS del tótem | C26: =INDEX(BOM!$I$9:$I$208,MATCH($A26,BOM!$A$9:$A$208,0)) -> Zona Industrial | D26: =INDEX(BOM!$G$9:$G$208,MATCH($A26,BOM!$A$9:$A$208,0))-SUMIF($A$6:$A$16,$A26,$D$6:$D$16) -> 2 | E26: =INDEX(BOM!$K$9:$K$208,MATCH($A26,BOM!$A$9:$A$208,0)) -> 5000 | F26: =D26*E26 -> 10000 | G26: =INDEX(BOM!$J$9:$J$208,MATCH($A26,BOM!$A$9:$A$208,0)) -> https://www.zonaindustrial.cl/shop/category/4324 | H26: Electrónica completa del tótem
A27: E08 | B27: =INDEX(BOM!$D$9:$D$208,MATCH($A27,BOM!$A$9:$A$208,0)) -> LED RGB de estado + resistencias | C27: =INDEX(BOM!$I$9:$I$208,MATCH($A27,BOM!$A$9:$A$208,0)) -> AFEL | D27: =INDEX(BOM!$G$9:$G$208,MATCH($A27,BOM!$A$9:$A$208,0))-SUMIF($A$6:$A$16,$A27,$D$6:$D$16) -> 2 | E27: =INDEX(BOM!$K$9:$K$208,MATCH($A27,BOM!$A$9:$A$208,0)) -> 1500 | F27: =D27*E27 -> 3000 | G27: =INDEX(BOM!$J$9:$J$208,MATCH($A27,BOM!$A$9:$A$208,0)) -> https://afel.cl/collections/leds | H27: Electrónica completa del tótem
A28: E09 | B28: =INDEX(BOM!$D$9:$D$208,MATCH($A28,BOM!$A$9:$A$208,0)) -> Buzzer del tótem (alto volumen) | C28: =INDEX(BOM!$I$9:$I$208,MATCH($A28,BOM!$A$9:$A$208,0)) -> AFEL | D28: =INDEX(BOM!$G$9:$G$208,MATCH($A28,BOM!$A$9:$A$208,0))-SUMIF($A$6:$A$16,$A28,$D$6:$D$16) -> 2 | E28: =INDEX(BOM!$K$9:$K$208,MATCH($A28,BOM!$A$9:$A$208,0)) -> 1500 | F28: =D28*E28 -> 3000 | G28: =INDEX(BOM!$J$9:$J$208,MATCH($A28,BOM!$A$9:$A$208,0)) -> https://afel.cl/collections/buzzer-zumbador | H28: Electrónica completa del tótem
A29: E10 | B29: =INDEX(BOM!$D$9:$D$208,MATCH($A29,BOM!$A$9:$A$208,0)) -> Transistores / módulo MOSFET | C29: =INDEX(BOM!$I$9:$I$208,MATCH($A29,BOM!$A$9:$A$208,0)) -> AFEL | D29: =INDEX(BOM!$G$9:$G$208,MATCH($A29,BOM!$A$9:$A$208,0))-SUMIF($A$6:$A$16,$A29,$D$6:$D$16) -> 2 | E29: =INDEX(BOM!$K$9:$K$208,MATCH($A29,BOM!$A$9:$A$208,0)) -> 1500 | F29: =D29*E29 -> 3000 | G29: =INDEX(BOM!$J$9:$J$208,MATCH($A29,BOM!$A$9:$A$208,0)) -> https://afel.cl/collections/mosfet | H29: Electrónica completa del tótem
A30: E11 | B30: =INDEX(BOM!$D$9:$D$208,MATCH($A30,BOM!$A$9:$A$208,0)) -> Buzzer del clip | C30: =INDEX(BOM!$I$9:$I$208,MATCH($A30,BOM!$A$9:$A$208,0)) -> AFEL | D30: =INDEX(BOM!$G$9:$G$208,MATCH($A30,BOM!$A$9:$A$208,0))-SUMIF($A$6:$A$16,$A30,$D$6:$D$16) -> 2 | E30: =INDEX(BOM!$K$9:$K$208,MATCH($A30,BOM!$A$9:$A$208,0)) -> 800 | F30: =D30*E30 -> 1600 | G30: =INDEX(BOM!$J$9:$J$208,MATCH($A30,BOM!$A$9:$A$208,0)) -> https://afel.cl/collections/buzzer-zumbador | H30: Pitido de los clips 2 y 3
A31: E12 | B31: =INDEX(BOM!$D$9:$D$208,MATCH($A31,BOM!$A$9:$A$208,0)) -> Interruptor del clip | C31: =INDEX(BOM!$I$9:$I$208,MATCH($A31,BOM!$A$9:$A$208,0)) -> AFEL | D31: =INDEX(BOM!$G$9:$G$208,MATCH($A31,BOM!$A$9:$A$208,0))-SUMIF($A$6:$A$16,$A31,$D$6:$D$16) -> 2 | E31: =INDEX(BOM!$K$9:$K$208,MATCH($A31,BOM!$A$9:$A$208,0)) -> 500 | F31: =D31*E31 -> 1000 | G31: =INDEX(BOM!$J$9:$J$208,MATCH($A31,BOM!$A$9:$A$208,0)) -> https://afel.cl/collections/botones-interruptores | H31: Interruptor de los clips 2 y 3
A32: E13 | B32: =INDEX(BOM!$D$9:$D$208,MATCH($A32,BOM!$A$9:$A$208,0)) -> Antena LoRa 915 MHz (tótem) | C32: =INDEX(BOM!$I$9:$I$208,MATCH($A32,BOM!$A$9:$A$208,0)) -> HUBOT | D32: =INDEX(BOM!$G$9:$G$208,MATCH($A32,BOM!$A$9:$A$208,0))-SUMIF($A$6:$A$16,$A32,$D$6:$D$16) -> 2 | E32: =INDEX(BOM!$K$9:$K$208,MATCH($A32,BOM!$A$9:$A$208,0)) -> 4990 | F32: =D32*E32 -> 9980 | G32: =INDEX(BOM!$J$9:$J$208,MATCH($A32,BOM!$A$9:$A$208,0)) -> https://hubot.cl/producto/antena-915mhz-2-5dbi-sma-lora-lorawan/ | H32: Solo si el alcance con la antena incluida en la Heltec no basta
... A53: T01 | B53: =INDEX(BOM!$D$9:$D$208,MATCH($A53,BOM!$A$9:$A$208,0)) -> Silicona neutra + gel de sílice | C53: =INDEX(BOM!$I$9:$I$208,MATCH($A53,BOM!$A$9:$A$208,0)) -> Ferretería | D53: =INDEX(BOM!$G$9:$G$208,MATCH($A53,BOM!$A$9:$A$208,0))-SUMIF($A$6:$A$16,$A53,$D$6:$D$16) -> 1 | E53: =INDEX(BOM!$K$9:$K$208,MATCH($A53,BOM!$A$9:$A$208,0)) -> 3500 | F53: =D53*E53 -> 3500 | G53: =INDEX(BOM!$J$9:$J$208,MATCH($A53,BOM!$A$9:$A$208,0)) -> Sin enlace verificado | H53: Montaje final del tótem en terreno
A54: Total fase 2 | F54: =SUM(F21:F53) -> 323914
A56: Control
A57: Fase 1 + Fase 2 | F57: =F17+F54 -> 432314
A58: Total hoja BOM | F58: =BOM!F2 -> 432314
A59: Diferencia (debe ser 0) | F59: =F57-F58 -> 0

Sheet Trazabilidad
A1: Trazabilidad arquitectura ↔ BOM
A2: Liste aquí las funciones de su arquitectura. Cada función física debería tener al menos un ítem en el BOM.
A4: Función | B4: Capa | C4: Descripción | D4: N° ítems en BOM | E4: Costo asociado (CLP) | F4: Estado
A5: Procesar y comunicar vía LoRa | B5: 4 Comunicación | C5: Procesar datos del tótem y transmitir por LoRa 915 MHz a la base, sin red celular (solo datos numéricos: ID, hora, clima, estado, SOS). | D5: =IF(A5="","",COUNTIF(BOM!$C$9:$C$208,A5)) -> 6 | E5: =IF(A5="","",SUMIF(BOM!$C$9:$C$208,A5,BOM!$L$9:$L$208)) -> 136710 | F5: =IF(A5="","",IF(D5=0,IF(B5="6 Información","Servicio / software (sin BOM físico)","Sin componente → falta en BOM"),"OK")) -> OK
A6: Identificar paso de senderista (clip BLE) | B6: 2 Interacción | C6: Detectar al senderista por el ID BLE de su clip cuando pasa cerca del tótem (reemplaza pulsera RFID pasiva). | D6: =IF(A6="","",COUNTIF(BOM!$C$9:$C$208,A6)) -> 1 | E6: =IF(A6="","",SUMIF(BOM!$C$9:$C$208,A6,BOM!$L$9:$L$208)) -> 28470 | F6: =IF(A6="","",IF(D6=0,IF(B6="6 Información","Servicio / software (sin BOM físico)","Sin componente → falta en BOM"),"OK")) -> OK
A7: Alertar al senderista con pitido (clip) | B7: 2 Interacción | C7: El clip pita cuando el tótem determina condición insegura (clima o hora límite). | D7: =IF(A7="","",COUNTIF(BOM!$C$9:$C$208,A7)) -> 1 | E7: =IF(A7="","",SUMIF(BOM!$C$9:$C$208,A7,BOM!$L$9:$L$208)) -> 2400 | F7: =IF(A7="","",IF(D7=0,IF(B7="6 Información","Servicio / software (sin BOM físico)","Sin componente → falta en BOM"),"OK")) -> OK
A8: Alimentar y encender el clip | B8: 3 Dispositivos | C8: Batería LiPo e interruptor del clip. | D8: =IF(A8="","",COUNTIF(BOM!$C$9:$C$208,A8)) -> 2 | E8: =IF(A8="","",SUMIF(BOM!$C$9:$C$208,A8,BOM!$L$9:$L$208)) -> 16500 | F8: =IF(A8="","",IF(D8=0,IF(B8="6 Información","Servicio / software (sin BOM físico)","Sin componente → falta en BOM"),"OK")) -> OK
A9: Medir clima y presión atmosférica | B9: 3 Dispositivos | C9: Presión, temperatura y humedad (BME280, fuera de la caja) para anticipar lluvia/viento. | D9: =IF(A9="","",COUNTIF(BOM!$C$9:$C$208,A9)) -> 1 | E9: =IF(A9="","",SUMIF(BOM!$C$9:$C$208,A9,BOM!$L$9:$L$208)) -> 17300 | F9: =IF(A9="","",IF(D9=0,IF(B9="6 Información","Servicio / software (sin BOM físico)","Sin componente → falta en BOM"),"OK")) -> OK
A10: Poner hora real y guardar registros (RTC) | B10: 5 Procesamiento | C10: Hora real en cada registro y reenvío si se corta LoRa (DS3231). | D10: =IF(A10="","",COUNTIF(BOM!$C$9:$C$208,A10)) -> 1 | E10: =IF(A10="","",SUMIF(BOM!$C$9:$C$208,A10,BOM!$L$9:$L$208)) -> 7000 | F10: =IF(A10="","",IF(D10=0,IF(B10="6 Información","Servicio / software (sin BOM físico)","Sin componente → falta en BOM"),"OK")) -> OK
A11: Emitir señal de auxilio manual (SOS en tótem) | B11: 2 Interacción | C11: Botón físico SOS en el tótem (no en el clip): llega a la base y al guardaparque. | D11: =IF(A11="","",COUNTIF(BOM!$C$9:$C$208,A11)) -> 1 | E11: =IF(A11="","",SUMIF(BOM!$C$9:$C$208,A11,BOM!$L$9:$L$208)) -> 10000 | F11: =IF(A11="","",IF(D11=0,IF(B11="6 Información","Servicio / software (sin BOM físico)","Sin componente → falta en BOM"),"OK")) -> OK
A12: Mostrar estado y alertas locales | B12: 2 Interacción | C12: LED, buzzer y OLED del tótem; manejo por transistores. | D12: =IF(A12="","",COUNTIF(BOM!$C$9:$C$208,A12)) -> 3 | E12: =IF(A12="","",SUMIF(BOM!$C$9:$C$208,A12,BOM!$L$9:$L$208)) -> 9000 | F12: =IF(A12="","",IF(D12=0,IF(B12="6 Información","Servicio / software (sin BOM físico)","Sin componente → falta en BOM"),"OK")) -> OK
A13: Alimentar nodo de forma autónoma | B13: 3 Dispositivos | C13: Panel 20 W + controlador PWM + batería AGM 12 V 7 Ah por tótem. | D13: =IF(A13="","",COUNTIF(BOM!$C$9:$C$208,A13)) -> 3 | E13: =IF(A13="","",SUMIF(BOM!$C$9:$C$208,A13,BOM!$L$9:$L$208)) -> 97274 | F13: =IF(A13="","",IF(D13=0,IF(B13="6 Información","Servicio / software (sin BOM físico)","Sin componente → falta en BOM"),"OK")) -> OK
A14: Convertir y proteger la energía (5 V / fusible) | B14: 5 Procesamiento | C14: Bajar 12 V a 5 V para la Heltec y proteger con fusible. | D14: =IF(A14="","",COUNTIF(BOM!$C$9:$C$208,A14)) -> 2 | E14: =IF(A14="","",SUMIF(BOM!$C$9:$C$208,A14,BOM!$L$9:$L$208)) -> 10000 | F14: =IF(A14="","",IF(D14=0,IF(B14="6 Información","Servicio / software (sin BOM físico)","Sin componente → falta en BOM"),"OK")) -> OK
A15: Sostener estructura de tótem (1:1) | B15: Estructura física | C15: Poste a escala real 1:1 para validar ergonomía y visibilidad. | D15: =IF(A15="","",COUNTIF(BOM!$C$9:$C$208,A15)) -> 1 | E15: =IF(A15="","",SUMIF(BOM!$C$9:$C$208,A15,BOM!$L$9:$L$208)) -> 29980 | F15: =IF(A15="","",IF(D15=0,IF(B15="6 Información","Servicio / software (sin BOM físico)","Sin componente → falta en BOM"),"OK")) -> OK
A16: Proteger componentes contra intemperie | B16: Estructura física | C16: Caja IP65, prensaestopas, silicona y gel de sílice contra lluvia y condensación. | D16: =IF(A16="","",COUNTIF(BOM!$C$9:$C$208,A16)) -> 3 | E16: =IF(A16="","",SUMIF(BOM!$C$9:$C$208,A16,BOM!$L$9:$L$208)) -> 21480 | F16: =IF(A16="","",IF(D16=0,IF(B16="6 Información","Servicio / software (sin BOM físico)","Sin componente → falta en BOM"),"OK")) -> OK
... A21: Monitorear aforo y alertas en portería | B21: 6 Información | C21: Dashboard web de guardaparques con aforo, clima y alertas SOS. | D21: =IF(A21="","",COUNTIF(BOM!$C$9:$C$208,A21)) -> 0 | E21: =IF(A21="","",SUMIF(BOM!$C$9:$C$208,A21,BOM!$L$9:$L$208)) -> 0 | F21: =IF(A21="","",IF(D21=0,IF(B21="6 Información","Servicio / software (sin BOM físico)","Sin componente → falta en BOM"),"OK")) -> Servicio / software (sin BOM físico)
D22: =IF(A22="","",COUNTIF(BOM!$C$9:$C$208,A22)) | E22: =IF(A22="","",SUMIF(BOM!$C$9:$C$208,A22,BOM!$L$9:$L$208)) | F22: =IF(A22="","",IF(D22=0,IF(B22="6 Información","Servicio / software (sin BOM físico)","Sin componente → falta en BOM"),"OK"))
D23: =IF(A23="","",COUNTIF(BOM!$C$9:$C$208,A23)) | E23: =IF(A23="","",SUMIF(BOM!$C$9:$C$208,A23,BOM!$L$9:$L$208)) | F23: =IF(A23="","",IF(D23=0,IF(B23="6 Información","Servicio / software (sin BOM físico)","Sin componente → falta en BOM"),"OK"))
D24: =IF(A24="","",COUNTIF(BOM!$C$9:$C$208,A24)) | E24: =IF(A24="","",SUMIF(BOM!$C$9:$C$208,A24,BOM!$L$9:$L$208)) | F24: =IF(A24="","",IF(D24=0,IF(B24="6 Información","Servicio / software (sin BOM físico)","Sin componente → falta en BOM"),"OK"))
D25: =IF(A25="","",COUNTIF(BOM!$C$9:$C$208,A25)) | E25: =IF(A25="","",SUMIF(BOM!$C$9:$C$208,A25,BOM!$L$9:$L$208)) | F25: =IF(A25="","",IF(D25=0,IF(B25="6 Información","Servicio / software (sin BOM físico)","Sin componente → falta en BOM"),"OK"))
D26: =IF(A26="","",COUNTIF(BOM!$C$9:$C$208,A26)) | E26: =IF(A26="","",SUMIF(BOM!$C$9:$C$208,A26,BOM!$L$9:$L$208)) | F26: =IF(A26="","",IF(D26=0,IF(B26="6 Información","Servicio / software (sin BOM físico)","Sin componente → falta en BOM"),"OK"))
D27: =IF(A27="","",COUNTIF(BOM!$C$9:$C$208,A27)) | E27: =IF(A27="","",SUMIF(BOM!$C$9:$C$208,A27,BOM!$L$9:$L$208)) | F27: =IF(A27="","",IF(D27=0,IF(B27="6 Información","Servicio / software (sin BOM físico)","Sin componente → falta en BOM"),"OK"))
D28: =IF(A28="","",COUNTIF(BOM!$C$9:$C$208,A28)) | E28: =IF(A28="","",SUMIF(BOM!$C$9:$C$208,A28,BOM!$L$9:$L$208)) | F28: =IF(A28="","",IF(D28=0,IF(B28="6 Información","Servicio / software (sin BOM físico)","Sin componente → falta en BOM"),"OK"))
D29: =IF(A29="","",COUNTIF(BOM!$C$9:$C$208,A29)) | E29: =IF(A29="","",SUMIF(BOM!$C$9:$C$208,A29,BOM!$L$9:$L$208)) | F29: =IF(A29="","",IF(D29=0,IF(B29="6 Información","Servicio / software (sin BOM físico)","Sin componente → falta en BOM"),"OK"))
D30: =IF(A30="","",COUNTIF(BOM!$C$9:$C$208,A30)) | E30: =IF(A30="","",SUMIF(BOM!$C$9:$C$208,A30,BOM!$L$9:$L$208)) | F30: =IF(A30="","",IF(D30=0,IF(B30="6 Información","Servicio / software (sin BOM físico)","Sin componente → falta en BOM"),"OK"))
D31: =IF(A31="","",COUNTIF(BOM!$C$9:$C$208,A31)) | E31: =IF(A31="","",SUMIF(BOM!$C$9:$C$208,A31,BOM!$L$9:$L$208)) | F31: =IF(A31="","",IF(D31=0,IF(B31="6 Información","Servicio / software (sin BOM físico)","Sin componente → falta en BOM"),"OK"))
D32: =IF(A32="","",COUNTIF(BOM!$C$9:$C$208,A32)) | E32: =IF(A32="","",SUMIF(BOM!$C$9:$C$208,A32,BOM!$L$9:$L$208)) | F32: =IF(A32="","",IF(D32=0,IF(B32="6 Información","Servicio / software (sin BOM físico)","Sin componente → falta en BOM"),"OK"))
D33: =IF(A33="","",COUNTIF(BOM!$C$9:$C$208,A33)) | E33: =IF(A33="","",SUMIF(BOM!$C$9:$C$208,A33,BOM!$L$9:$L$208)) | F33: =IF(A33="","",IF(D33=0,IF(B33="6 Información","Servicio / software (sin BOM físico)","Sin componente → falta en BOM"),"OK"))
... D60: =IF(A60="","",COUNTIF(BOM!$C$9:$C$208,A60)) | E60: =IF(A60="","",SUMIF(BOM!$C$9:$C$208,A60,BOM!$L$9:$L$208)) | F60: =IF(A60="","",IF(D60=0,IF(B60="6 Información","Servicio / software (sin BOM físico)","Sin componente → falta en BOM"),"OK"))

Sheet Resumen
A1: Resumen por subsistema
A3: Subsistema | B3: N° ítems | C3: Costo (CLP) | D3: % del total | E3: Ítems sin precio
A4: Electrónica | B4: =COUNTIF(BOM!$B$9:$B$208,A4) -> 22 | C4: =SUMIF(BOM!$B$9:$B$208,A4,BOM!$L$9:$L$208) -> 337654 | D4: =IF($C$10=0,0,C4/$C$10) -> 0.78103878 | E4: =COUNTIFS(BOM!$B$9:$B$208,A4,BOM!$K$9:$K$208,"") -> 0
A5: Mecánica / estructura | B5: =COUNTIF(BOM!$B$9:$B$208,A5) -> 4 | C5: =SUMIF(BOM!$B$9:$B$208,A5,BOM!$L$9:$L$208) -> 50860 | D5: =IF($C$10=0,0,C5/$C$10) -> 0.11764597 | E5: =COUNTIFS(BOM!$B$9:$B$208,A5,BOM!$K$9:$K$208,"") -> 0
A6: Fabricación | B6: =COUNTIF(BOM!$B$9:$B$208,A6) -> 0 | C6: =SUMIF(BOM!$B$9:$B$208,A6,BOM!$L$9:$L$208) -> 0 | D6: =IF($C$10=0,0,C6/$C$10) -> 0 | E6: =COUNTIFS(BOM!$B$9:$B$208,A6,BOM!$K$9:$K$208,"") -> 0
A7: Terminaciones | B7: =COUNTIF(BOM!$B$9:$B$208,A7) -> 1 | C7: =SUMIF(BOM!$B$9:$B$208,A7,BOM!$L$9:$L$208) -> 3500 | D7: =IF($C$10=0,0,C7/$C$10) -> 0.0080959673 | E7: =COUNTIFS(BOM!$B$9:$B$208,A7,BOM!$K$9:$K$208,"") -> 0
A8: Ensamblaje | B8: =COUNTIF(BOM!$B$9:$B$208,A8) -> 9 | C8: =SUMIF(BOM!$B$9:$B$208,A8,BOM!$L$9:$L$208) -> 40300 | D8: =IF($C$10=0,0,C8/$C$10) -> 0.09321928 | E8: =COUNTIFS(BOM!$B$9:$B$208,A8,BOM!$K$9:$K$208,"") -> 0
A9: Según el proyecto | B9: =COUNTIF(BOM!$B$9:$B$208,A9) -> 0 | C9: =SUMIF(BOM!$B$9:$B$208,A9,BOM!$L$9:$L$208) -> 0 | D9: =IF($C$10=0,0,C9/$C$10) -> 0 | E9: =COUNTIFS(BOM!$B$9:$B$208,A9,BOM!$K$9:$K$208,"") -> 0
A10: Total | B10: =SUM(B4:B9) -> 36 | C10: =SUM(C4:C9) -> 432314 | D10: =SUM(D4:D9) -> 1 | E10: =SUM(E4:E9) -> 0
A12: El costo solo considera ítems con precio. Revise «Ítems sin precio» antes de presentar un presupuesto.

Sheet Historial
A1: Historial de versiones
A3: Versión | B3: Fecha | C3: Autor | D3: Qué cambió | E3: Por qué | F3: Ítems afectados (ID) | G3: Efecto en costo (CLP)
A4: BOM_v01 | B4: 28-09-2026 | C4: Valeria Cheetham | D4: BOM inicial basado en arquitectura de trazabilidad por pórticos LoRa y pulseras RFID. | E4: Acotar alcance: medir tiempo y clima barométrico, descartar biometría compleja y dar soporte a pórtico 1:1 + maquetas a escala. | F4: E01–A01 | G4: 168500
A5: BOM_v1.1 | B5: 01-10-2026 | C5: Maximiliano Greve | D5: Arquitectura 1.1. (1) Se elimina el lector RFID RC522 y la pulsera pasiva; se agrega clip BLE activo con XIAO ESP32-C3, LiPo, buzzer, interruptor y pinza (E03, E04, E11, E12, M03). (2) El SOS pasa al tótem y se duplica (E07). (3) La Heltec V3 del tótem decide seguro/inseguro y se separa de la base: E01 tótem ×2, E02 base ×1. (4) Se agregan RTC DS3231 (E06), transistores (E10), antena 915 MHz con pigtail U.FL→SMA (E13–E16) y cable USB de datos (E17). (5) Energía: se reemplaza panel 5,5 V + 18650 + TP4056 por panel 20 W, controlador PWM, batería AGM 12 V 7 Ah, fusible 5 A y LM2596 12→5 V (E18–E22). (6) BME280, SOS, LED, buzzer, poste y caja pasan a ×2 (un juego por tótem); LED RGB reemplaza al WS2812B. Se elimina el filamento 3D (no se imprimirá nada) y se agrega mini caja plástica para el clip (M04). (7) Cableado desglosado y se agrega sellado (A01–A09, T01). (8) Se descarta la cámara y el SOS en la pulsera. Se agrega la hoja Fases: Fase 1 (11 ítems, $108.400) para probar el alcance LoRa caseta↔Cerro La Cruz con las antenas incluidas, y Fase 2 (el resto, incluida la cadena solar) solo si la prueba funciona. | E5: Barreras detectadas: LoRa no sirve para imágenes; RFID alcanza solo centímetros y no puede avisar al senderista; el clip no tiene LoRa, así que el SOS solo puede ir en el tótem; el panel de 170 mA no alimenta BLE + LoRa; el GPIO de la Heltec no maneja un buzzer fuerte; la Heltec V3 no tolera 12 V; el BME280 dentro de la caja mide mal; la batería AGM no cabe en la caja; LoRa en Chile usa 915 MHz (los módulos de 433 MHz no sirven). Se corrigió además el MPN del SOS (decía WS2812B) (el filamento de v01 ya no aplica). | F5: Todos (E01–E22, M01–M04, A01–A09, T01). Eliminados de v01: lector RFID, pulsera RFID, panel 5,5 V + 18650 + TP4056. | G5: =BOM!F2-G4 -> 263814

Sheet Listas
A1: Subsistema | B1: Unidad | C1: Disponibilidad | D1: Estado | E1: Capa
A2: Electrónica | B2: un. | C2: Disponible en Chile | D2: Por cotizar | E2: 1 Personas / contexto
A3: Mecánica / estructura | B3: m | C3: Importación | D3: Cotizado | E3: 2 Interacción
A4: Fabricación | B4: m² | C4: Sin stock | D4: Comprado | E4: 3 Dispositivos
A5: Terminaciones | B5: cm | C5: Por verificar | D5: Recibido | E5: 4 Comunicación
A6: Ensamblaje | B6: kg | D6: Instalado | E6: 5 Procesamiento
A7: Según el proyecto | B7: g | D7: Descartado | E7: 6 Información
B8: ml | E8: 7 Servicios
B9: set | E9: Estructura física
B10: hr
